bip32template/__init__.py
tests/__init__.py
tests/test_templates.py
bip32template-0.0.4.dist-info/LICENSE
bip32template-0.0.4.dist-info/METADATA
bip32template-0.0.4.dist-info/WHEEL
bip32template-0.0.4.dist-info/top_level.txt
bip32template-0.0.4.dist-info/RECORD
