Metadata-Version: 2.1
Name: bip32template
Version: 0.0.4
Summary: Reference implementation of BIP32 templates
Home-page: https://github.com/dgpv/bip32_template_python_implementation
License: UNKNOWN
Keywords: bitcoin bip32
Platform: UNKNOWN
Classifier: Programming Language :: Python :: 3.6
Classifier: Programming Language :: Python :: 3.7
Classifier: Programming Language :: Python :: 3.8
Classifier: License :: OSI Approved :: MIT License
Requires-Python: >=3.6
